gwcelery/__init__.py
gwcelery/flask.py
gwcelery/jinja.py
gwcelery/views.py
gwcelery/conf/__init__.py
gwcelery/conf/dev.py
gwcelery/conf/minikube.py
gwcelery/conf/playground.py
gwcelery/conf/production.py
gwcelery/conf/test.py
gwcelery/data/__init__.py
gwcelery/data/first2years/__init__.py
gwcelery/data/first2years/gstlal.xml.gz
gwcelery/email/__init__.py
gwcelery/email/bootsteps.py
gwcelery/email/signals.py
gwcelery/igwn_alert/__init__.py
gwcelery/igwn_alert/bootsteps.py
gwcelery/igwn_alert/signals.py
gwcelery/kafka/__init__.py
gwcelery/kafka/bootsteps.py
gwcelery/kafka/signals.py
gwcelery/sentry/__init__.py
gwcelery/sentry/integrations/__init__.py
gwcelery/sentry/integrations/condor.py
gwcelery/sentry/integrations/requests.py
gwcelery/sentry/integrations/subprocess.py
gwcelery/static/typeahead.css
gwcelery/static/vega/index.html
gwcelery/tasks/__init__.py
gwcelery/tasks/alerts.py
gwcelery/tasks/bayestar.py
gwcelery/tasks/circulars.py
gwcelery/tasks/condor.py
gwcelery/tasks/core.py
gwcelery/tasks/detchar.py
gwcelery/tasks/em_bright.py
gwcelery/tasks/external_skymaps.py
gwcelery/tasks/external_triggers.py
gwcelery/tasks/first2years.py
gwcelery/tasks/first2years_external.py
gwcelery/tasks/gcn.py
gwcelery/tasks/gracedb.py
gwcelery/tasks/gwskynet.py
gwcelery/tasks/igwn_alert.py
gwcelery/tasks/inference.py
gwcelery/tasks/legacy_gracedb.py
gwcelery/tasks/mchirp_estimates.py
gwcelery/tasks/notice_text.py
gwcelery/tasks/orchestrator.py
gwcelery/tasks/p_astro.py
gwcelery/tasks/raven.py
gwcelery/tasks/rrt_utils.py
gwcelery/tasks/skymaps.py
gwcelery/tasks/superevents.py
gwcelery/templates/fits_header.jinja2
gwcelery/templates/index.jinja2
gwcelery/templates/lalinference.jinja2
gwcelery/templates/rapidpe.jinja2
gwcelery/templates/sccb_template.jinja2
gwcelery/templates/vector_table.jinja2
gwcelery/tests/__init__.py
gwcelery/tests/conftest.py
gwcelery/tests/process.py
gwcelery/tests/test_sentry.py
gwcelery/tests/test_tasks_alerts.py
gwcelery/tests/test_tasks_alerts_validate.py
gwcelery-2.10.0.dist-info/licenses/LICENSE.rst
gwcelery-2.10.0.dist-info/METADATA
gwcelery-2.10.0.dist-info/WHEEL
gwcelery-2.10.0.dist-info/entry_points.txt
gwcelery-2.10.0.dist-info/top_level.txt
gwcelery-2.10.0.dist-info/RECORD
